mmkfeatures/__init__.py
mmkfeatures/fusion/__init__.py
mmkfeatures/fusion/blank.py
mmkfeatures/fusion/computational_sequence.py
mmkfeatures/fusion/download_ops.py
mmkfeatures/fusion/file_ops.py
mmkfeatures/fusion/integrity_check.py
mmkfeatures/fusion/log.py
mmkfeatures/fusion/metadataconfigs.py
mmk_features-0.0.1.dev0.dist-info/LICENSE
mmk_features-0.0.1.dev0.dist-info/METADATA
mmk_features-0.0.1.dev0.dist-info/WHEEL
mmk_features-0.0.1.dev0.dist-info/top_level.txt
mmk_features-0.0.1.dev0.dist-info/RECORD
